abtpackage/__init__.py
abtpackage-1.0.1.dist-info/LICENSE
abtpackage-1.0.1.dist-info/METADATA
abtpackage-1.0.1.dist-info/WHEEL
abtpackage-1.0.1.dist-info/top_level.txt
abtpackage-1.0.1.dist-info/RECORD
