Metadata-Version: 2.1
Name: abtpackage
Version: 1.0.1
Summary: abtpackage Public Interface
Home-page: UNKNOWN
Author: Ashta Bhuja Tripathi
Author-email: tripathiab13@gmail.com
License: UNKNOWN
Platform: UNKNOWN
Classifier: Programming Language :: Python :: 3
Classifier: License :: OSI Approved :: MIT License
Classifier: Operating System :: OS Independent
